MANIFEST.in
README.md
setup.cfg
setup.py
clustergrammer_widget/__init__.py
clustergrammer_widget/_version.py
clustergrammer_widget/example.py
clustergrammer_widget.egg-info/PKG-INFO
clustergrammer_widget.egg-info/SOURCES.txt
clustergrammer_widget.egg-info/dependency_links.txt
clustergrammer_widget.egg-info/not-zip-safe
clustergrammer_widget.egg-info/requires.txt
clustergrammer_widget.egg-info/top_level.txt
clustergrammer_widget/clustergrammer/__init__.py
clustergrammer_widget/clustergrammer/calc_clust.py
clustergrammer_widget/clustergrammer/cat_pval.py
clustergrammer_widget/clustergrammer/categories.py
clustergrammer_widget/clustergrammer/data_formats.py
clustergrammer_widget/clustergrammer/downsample_fun.py
clustergrammer_widget/clustergrammer/enrichr_functions.py
clustergrammer_widget/clustergrammer/export_data.py
clustergrammer_widget/clustergrammer/iframe_web_app.py
clustergrammer_widget/clustergrammer/initialize_net.py
clustergrammer_widget/clustergrammer/load_data.py
clustergrammer_widget/clustergrammer/load_vect_post.py
clustergrammer_widget/clustergrammer/make_clust_fun.py
clustergrammer_widget/clustergrammer/make_sim_mat.py
clustergrammer_widget/clustergrammer/make_unique_labels.py
clustergrammer_widget/clustergrammer/make_views.py
clustergrammer_widget/clustergrammer/make_viz.py
clustergrammer_widget/clustergrammer/normalize_fun.py
clustergrammer_widget/clustergrammer/proc_df_labels.py
clustergrammer_widget/clustergrammer/run_filter.py
clustergrammer_widget/static/extension.js
clustergrammer_widget/static/f2c72c12e473db657b6f061871c24289.png
clustergrammer_widget/static/index.js
clustergrammer_widget/static/index.js.map